torchnca/__init__.py
torchnca/nca.py
torchnca-0.1.0.dist-info/LICENSE
torchnca-0.1.0.dist-info/METADATA
torchnca-0.1.0.dist-info/WHEEL
torchnca-0.1.0.dist-info/top_level.txt
torchnca-0.1.0.dist-info/RECORD
