Metadata-Version: 2.1
Name: torchnca
Version: 0.1.0
Summary: Neighbourhood Components Analysis in PyTorch.
Home-page: https://github.com/kevinzakka/nca
Author: Kevin Zakka
Author-email: kevinarmandzakka@gmail.com
License: MIT
Keywords: ai metric learning nearest neighbours dimensionality reduction
Platform: UNKNOWN
Classifier: Programming Language :: Python :: 3
Classifier: License :: OSI Approved :: MIT License
Classifier: Operating System :: OS Independent
Requires-Python: >=3.5
Requires-Dist: numpy (<2.0.0,>=1.0.0)
Requires-Dist: torch (<=1.4.0,>=1.0.0)
